{"nodes":[{"id":"jest_0","type":"start","data":{"url":"https://juejin.cn/"},"position":{"x":233.18351106998705,"y":-82.21394588006325},"width":260,"height":113,"selected":false,"positionAbsolute":{"x":233.18351106998705,"y":-82.21394588006325},"dragging":false},{"id":"cc3cn2vq8rg","position":{"x":214.60254304994976,"y":94.3591878850726},"type":"opt_click","data":{"optsetting":{"xpath":"/html/body/div[1]/div[1]/div[@id=\"juejin\"]/div[1]/main[1]/div[1]/div[2]/div[1]/div[1]/div[1]/div[1]/div[1]/li[1]/div[1]/div[1]/div[1]/div[1]/a[1]","waitTime":0,"optType":"opt_click","clickData":{"isCurrentPage":1}}},"width":300,"height":113,"selected":true,"positionAbsolute":{"x":214.60254304994976,"y":94.3591878850726},"dragging":false}],"edges":[{"source":"jest_0","sourceHandle":null,"target":"cc3cn2vq8rg","targetHandle":null,"id":"reactflow__edge-jest_0-cc3cn2vq8rg"}],"task":"[{\"nodeType\":\"start\",\"url\":\"https://juejin.cn/\"},{\"nodeType\":\"opt\",\"optsetting\":{\"xpath\":\"/html/body/div[1]/div[1]/div[@id=\\\"juejin\\\"]/div[1]/main[1]/div[1]/div[2]/div[1]/div[1]/div[1]/div[1]/div[1]/li[1]/div[1]/div[1]/div[1]/div[1]/a[1]\",\"waitTime\":0,\"optType\":\"opt_click\",\"clickData\":{\"isCurrentPage\":1}}}]"}